Metadata-Version: 2.4
Name: llm-fragments-github
Version: 0.4
Summary: Load GitHub repository contents as LLM fragments
Author: Simon Willison
License-Expression: Apache-2.0
Project-URL: Homepage, https://github.com/simonw/llm-fragments-github
Project-URL: Changelog, https://github.com/simonw/llm-fragments-github/releases
Project-URL: Issues, https://github.com/simonw/llm-fragments-github/issues
Project-URL: CI, https://github.com/simonw/llm-fragments-github/actions
Requires-Python: >=3.9
License-File: LICENSE
Requires-Dist: llm
Provides-Extra: test
Requires-Dist: pytest; extra == "test"
Requires-Dist: pytest-httpx; extra == "test"
Dynamic: license-file
